basalt/__init__.py
basalt/tasks/__init__.py
basalt/tasks/config_generator.py
basalt/tasks/dict_config_parser.py
basalt/tasks/fs_commands.py
basalt/tasks/package_generator.py
basalt/tasks/simple_version.py
basalt/tasks/utils.py
basalt/tasks/vcs_info.py
basalt_tasks-0.2.dist-info/DESCRIPTION.rst
basalt_tasks-0.2.dist-info/METADATA
basalt_tasks-0.2.dist-info/RECORD
basalt_tasks-0.2.dist-info/WHEEL
basalt_tasks-0.2.dist-info/metadata.json
basalt_tasks-0.2.dist-info/top_level.txt
