Metadata-Version: 2.0
Name: basalt-tasks
Version: 0.2
Summary: Helper functions for the basalt invoke build file.
Home-page: https://github.com/basalt/python-basalt
Author: Jochen Breuer
Author-email: brejoc@gmail.com
License: MIT
Platform: any
Requires-Dist: Jinja2
Requires-Dist: PyYAML
Requires-Dist: invoke (==0.7.0)
Requires-Dist: sh
